{
  "rectangleOptions": {
    "name": "Rect",
    "draggable": true,
    "cornerRadius": 0,
    "stroke": "#000000",
    "strokeWidth": 0,
    "shadowColor": "#3c4043",
    "shadowBlur": 10,
    "shadowOffsetX": 10,
    "shadowOffsetY": 10,
    "shadowOpacity": 0,
    "opacity": 1,
    "rotation": 0,
    "scaleX": 1,
    "scaleY": 1
  },
  "circleOptions": {
    "name": "Circle",
    "draggable": true,
    "stroke": "#000000",
    "strokeWidth": 0,
    "shadowColor": "#3c4043",
    "shadowBlur": 10,
    "shadowOffsetX": 10,
    "shadowOffsetY": 10,
    "shadowOpacity": 0,
    "opacity": 1,
    "rotation": 0,
    "scaleX": 1,
    "scaleY": 1
  },
  "arrowOptions": {
    "id": "",
    "name": "arrow",
    "points": [0, 0, 50, 50],
    "pointerLength": 10,
    "pointerWidth": 10,
    "fill": "#ff0000",
    "stroke": "#000000",
    "strokeWidth": 2,
    "draggable": true,
    "shadowColor": "#333",
    "shadowBlur": 10,
    "shadowOffsetX": 5,
    "shadowOffsetY": 5,
    "shadowOpacity": 0,
    "opacity": 1,
    "rotation": 0,
    "scaleX": 1,
    "scaleY": 1,
    "tension": 0,
    "lineCap": "round"
  }
}
